oresat_c3/__init__.py
oresat_c3/__main__.py
oresat_c3/_version.py
oresat_c3/drivers/__init__.py
oresat_c3/drivers/fm24cl64b.py
oresat_c3/drivers/max7310.py
oresat_c3/drivers/si41xx.py
oresat_c3/protocols/__init__.py
oresat_c3/protocols/ax25.py
oresat_c3/protocols/cachestore.py
oresat_c3/protocols/cfdp.py
oresat_c3/protocols/edl_command.py
oresat_c3/protocols/edl_packet.py
oresat_c3/services/__init__.py
oresat_c3/services/beacon.py
oresat_c3/services/edl.py
oresat_c3/services/node_manager.py
oresat_c3/services/radios.py
oresat_c3/services/state.py
oresat_c3/subsystems/__init__.py
oresat_c3/subsystems/antennas.py
oresat_c3/subsystems/opd.py
oresat_c3/subsystems/rtc.py
oresat_c3/templates/beacon.html
oresat_c3/templates/keys.html
oresat_c3/templates/node_manager.html
oresat_c3/templates/state.html
oresat_c3-0.5.0.dist-info/LICENSE
oresat_c3-0.5.0.dist-info/METADATA
oresat_c3-0.5.0.dist-info/WHEEL
oresat_c3-0.5.0.dist-info/entry_points.txt
oresat_c3-0.5.0.dist-info/top_level.txt
oresat_c3-0.5.0.dist-info/RECORD
