Metadata-Version: 2.1
Name: oresat-c3
Version: 0.5.0
Summary: OreSat C3 OLAF app
License: GPL-3.0
Classifier: License :: OSI Approved :: GNU General Public License v3 (GPLv3)
Classifier: Operating System :: POSIX :: Linux
Classifier: Programming Language :: Python :: 3
Classifier: Programming Language :: Python :: 3.9
Classifier: Programming Language :: Python :: 3.10
Classifier: Programming Language :: Python :: 3.11
Classifier: Topic :: Software Development :: Embedded Systems
Requires-Python: >=3.9
License-File: LICENSE
Requires-Dist: bitstring
Requires-Dist: cfdp-py
Requires-Dist: dataclasses-json
Requires-Dist: oresat-configs
Requires-Dist: oresat-olaf >=3.5.0
Requires-Dist: smbus2
Requires-Dist: spacepackets
